{
  "ControlStates": {
    "Address": {
      "AllowAccessToGlobals": true,
      "ControlPropertyState": [
        "Live",
        "Overflow",
        {
          "AFDDataSourceName": "",
          "AutoRuleBindingEnabled": false,
          "AutoRuleBindingString": "ThisItem.Name",
          "InvariantPropertyName": "Text",
          "IsLockable": false,
          "NameMapSourceSchema": "?"
        },
        "Role",
        "Color",
        "DisabledColor",
        "PressedColor",
        "HoverColor",
        "BorderColor",
        "DisabledBorderColor",
        "PressedBorderColor",
        "HoverBorderColor",
        "BorderStyle",
        "FocusedBorderColor",
        "Fill",
        "DisabledFill",
        "PressedFill",
        "HoverFill",
        "Font",
        "FontWeight",
        "Align",
        "VerticalAlign",
        "X",
        "Y",
        "Width",
        "Height",
        "DisplayMode",
        "OnSelect",
        "ZIndex",
        "PaddingTop",
        "PaddingRight",
        "PaddingBottom",
        "PaddingLeft",
        "TabIndex",
        "Size"
      ],
      "HasDynamicProperties": false,
      "IsAutoGenerated": false,
      "IsComponentDefinition": false,
      "IsDataControl": false,
      "IsFromScreenLayout": false,
      "IsGroupControl": false,
      "IsLocked": false,
      "LayoutName": "",
      "MetaDataIDKey": "%TemplateBrowseGalleryBody.ID%",
      "Name": "Address",
      "OptimizeForDevices": "Off",
      "ParentIndex": 3,
      "PersistMetaDataIDKey": false,
      "Properties": [
        {
          "Category": "Data",
          "PropertyName": "Role",
          "RuleProviderType": "Unknown"
        },
        {
          "Category": "Data",
          "PropertyName": "Text",
          "RuleProviderType": "User"
        },
        {
          "Category": "Data",
          "PropertyName": "Live",
          "RuleProviderType": "Unknown"
        },
        {
          "Category": "Design",
          "PropertyName": "DisabledFill",
          "RuleProviderType": "Unknown"
        },
        {
          "Category": "Design",
          "PropertyName": "Fill",
          "RuleProviderType": "Unknown"
        },
        {
          "Category": "Design",
          "PropertyName": "BorderStyle",
          "RuleProviderType": "Unknown"
        },
        {
          "Category": "Design",
          "PropertyName": "DisabledBorderColor",
          "RuleProviderType": "Unknown"
        },
        {
          "Category": "Design",
          "PropertyName": "BorderColor",
          "RuleProviderType": "Unknown"
        },
        {
          "Category": "Design",
          "PropertyName": "DisabledColor",
          "RuleProviderType": "Unknown"
        },
        {
          "Category": "Design",
          "PropertyName": "DisplayMode",
          "RuleProviderType": "Unknown"
        },
        {
          "Category": "Design",
          "PropertyName": "ZIndex",
          "RuleProviderType": "Unknown"
        },
        {
          "Category": "Design",
          "PropertyName": "Color",
          "RuleProviderType": "Unknown"
        },
        {
          "Category": "Design",
          "PropertyName": "Font",
          "RuleProviderType": "Unknown"
        },
        {
          "Category": "Design",
          "PropertyName": "Align",
          "RuleProviderType": "Unknown"
        },
        {
          "Category": "Design",
          "PropertyName": "VerticalAlign",
          "RuleProviderType": "Unknown"
        },
        {
          "Category": "Design",
          "PropertyName": "Overflow",
          "RuleProviderType": "Unknown"
        },
        {
          "Category": "Design",
          "PropertyName": "TabIndex",
          "RuleProviderType": "Unknown"
        },
        {
          "Category": "Design",
          "PropertyName": "PaddingLeft",
          "RuleProviderType": "Unknown"
        },
        {
          "Category": "Design",
          "PropertyName": "X",
          "RuleProviderType": "Unknown"
        },
        {
          "Category": "Design",
          "PropertyName": "Width",
          "RuleProviderType": "Unknown"
        },
        {
          "Category": "Design",
          "PropertyName": "Y",
          "RuleProviderType": "Unknown"
        },
        {
          "Category": "Design",
          "PropertyName": "PressedColor",
          "RuleProviderType": "Unknown"
        },
        {
          "Category": "Design",
          "PropertyName": "PaddingTop",
          "RuleProviderType": "Unknown"
        },
        {
          "Category": "Design",
          "PropertyName": "PaddingRight",
          "RuleProviderType": "Unknown"
        },
        {
          "Category": "Design",
          "PropertyName": "FontWeight",
          "RuleProviderType": "Unknown"
        },
        {
          "Category": "Design",
          "PropertyName": "PaddingBottom",
          "RuleProviderType": "Unknown"
        },
        {
          "Category": "Design",
          "PropertyName": "Height",
          "RuleProviderType": "Unknown"
        },
        {
          "Category": "Design",
          "PropertyName": "Size",
          "RuleProviderType": "Unknown"
        },
        {
          "Category": "Design",
          "PropertyName": "HoverFill",
          "RuleProviderType": "Unknown"
        },
        {
          "Category": "Design",
          "PropertyName": "PressedFill",
          "RuleProviderType": "Unknown"
        },
        {
          "Category": "Design",
          "PropertyName": "FocusedBorderColor",
          "RuleProviderType": "Unknown"
        },
        {
          "Category": "Design",
          "PropertyName": "HoverBorderColor",
          "RuleProviderType": "Unknown"
        },
        {
          "Category": "Design",
          "PropertyName": "PressedBorderColor",
          "RuleProviderType": "Unknown"
        },
        {
          "Category": "Design",
          "PropertyName": "HoverColor",
          "RuleProviderType": "Unknown"
        },
        {
          "Category": "Behavior",
          "PropertyName": "OnSelect",
          "RuleProviderType": "Unknown"
        }
      ],
      "StyleName": "contentLabelStyle_galleryLayouts_ver5",
      "Type": "ControlInfo"
    },
    "DateFilter_Assignment_Screen": {
      "AllowAccessToGlobals": true,
      "ControlPropertyState": [
        {
          "AFDDataSourceName": "",
          "AutoRuleBindingEnabled": false,
          "AutoRuleBindingString": "",
          "InvariantPropertyName": "Fill",
          "IsLockable": false,
          "NameMapSourceSchema": "?"
        },
        "ImagePosition",
        "Height",
        "Width",
        "Size",
        "Orientation",
        "LoadingSpinner",
        "LoadingSpinnerColor"
      ],
      "IsAutoGenerated": false,
      "IsComponentDefinition": false,
      "IsDataControl": false,
      "IsFromScreenLayout": false,
      "IsGroupControl": false,
      "IsLocked": false,
      "LayoutName": "",
      "MetaDataIDKey": "",
      "Name": "DateFilter_Assignment_Screen",
      "OptimizeForDevices": "Off",
      "ParentIndex": 0,
      "PersistMetaDataIDKey": false,
      "Properties": [
        {
          "Category": "Design",
          "PropertyName": "Fill",
          "RuleProviderType": "User"
        },
        {
          "Category": "Design",
          "PropertyName": "ImagePosition",
          "RuleProviderType": "Unknown"
        },
        {
          "Category": "Design",
          "PropertyName": "Height",
          "RuleProviderType": "Unknown"
        },
        {
          "Category": "Design",
          "PropertyName": "Width",
          "RuleProviderType": "Unknown"
        },
        {
          "Category": "Design",
          "PropertyName": "Orientation",
          "RuleProviderType": "Unknown"
        },
        {
          "Category": "Design",
          "PropertyName": "Size",
          "RuleProviderType": "Unknown"
        },
        {
          "Category": "Design",
          "PropertyName": "LoadingSpinnerColor",
          "RuleProviderType": "Unknown"
        },
        {
          "Category": "Design",
          "PropertyName": "LoadingSpinner",
          "RuleProviderType": "Unknown"
        }
      ],
      "StyleName": "defaultScreenStyle",
      "Type": "ControlInfo"
    },
    "DatePicker2": {
      "AllowAccessToGlobals": true,
      "ControlPropertyState": [
        "DefaultDate",
        "DateTimeZone",
        "Format",
        "InputTextPlaceholder",
        "StartYear",
        "EndYear",
        "StartOfWeek",
        "IconFill",
        "IconBackground",
        "SelectedDateFill",
        "HoverDateFill",
        "CurrentDateFill",
        "CalendarHeaderFill",
        "MonthColor",
        "WeekColor",
        "DayColor",
        "BorderColor",
        "DisabledFill",
        "PressedFill",
        "HoverFill",
        "PressedBorderColor",
        "HoverBorderColor",
        "DisabledBorderColor",
        "BorderStyle",
        "FocusedBorderColor",
        "Fill",
        "Font",
        "FontWeight",
        "Color",
        "DisabledColor",
        "Width",
        "Height",
        "X",
        "Y",
        "DisplayMode",
        "ZIndex",
        "BorderThickness",
        "FocusedBorderThickness",
        "Size",
        "Italic",
        "PaddingTop",
        "PaddingRight",
        "PaddingBottom",
        "PaddingLeft",
        {
          "AFDDataSourceName": "",
          "AutoRuleBindingEnabled": false,
          "AutoRuleBindingString": "false",
          "InvariantPropertyName": "OnSelect",
          "IsLockable": false,
          "NameMapSourceSchema": "?"
        }
      ],
      "HasDynamicProperties": false,
      "IsAutoGenerated": false,
      "IsComponentDefinition": false,
      "IsDataControl": false,
      "IsFromScreenLayout": false,
      "IsGroupControl": false,
      "IsLocked": false,
      "LayoutName": "",
      "MetaDataIDKey": "",
      "Name": "DatePicker2",
      "OptimizeForDevices": "Off",
      "ParentIndex": 0,
      "PersistMetaDataIDKey": false,
      "Properties": [
        {
          "Category": "Data",
          "PropertyName": "DefaultDate",
          "RuleProviderType": "Unknown"
        },
        {
          "Category": "Data",
          "PropertyName": "DateTimeZone",
          "RuleProviderType": "Unknown"
        },
        {
          "Category": "Data",
          "PropertyName": "Format",
          "RuleProviderType": "Unknown"
        },
        {
          "Category": "Data",
          "PropertyName": "InputTextPlaceholder",
          "RuleProviderType": "Unknown"
        },
        {
          "Category": "Data",
          "PropertyName": "StartYear",
          "RuleProviderType": "Unknown"
        },
        {
          "Category": "Data",
          "PropertyName": "EndYear",
          "RuleProviderType": "Unknown"
        },
        {
          "Category": "Data",
          "PropertyName": "StartOfWeek",
          "RuleProviderType": "Unknown"
        },
        {
          "Category": "Design",
          "PropertyName": "IconFill",
          "RuleProviderType": "Unknown"
        },
        {
          "Category": "Design",
          "PropertyName": "IconBackground",
          "RuleProviderType": "Unknown"
        },
        {
          "Category": "Design",
          "PropertyName": "SelectedDateFill",
          "RuleProviderType": "Unknown"
        },
        {
          "Category": "Design",
          "PropertyName": "HoverDateFill",
          "RuleProviderType": "Unknown"
        },
        {
          "Category": "Design",
          "PropertyName": "CurrentDateFill",
          "RuleProviderType": "Unknown"
        },
        {
          "Category": "Design",
          "PropertyName": "CalendarHeaderFill",
          "RuleProviderType": "Unknown"
        },
        {
          "Category": "Design",
          "PropertyName": "MonthColor",
          "RuleProviderType": "Unknown"
        },
        {
          "Category": "Design",
          "PropertyName": "WeekColor",
          "RuleProviderType": "Unknown"
        },
        {
          "Category": "Design",
          "PropertyName": "DayColor",
          "RuleProviderType": "Unknown"
        },
        {
          "Category": "Design",
          "PropertyName": "BorderColor",
          "RuleProviderType": "Unknown"
        },
        {
          "Category": "Design",
          "PropertyName": "DisabledFill",
          "RuleProviderType": "Unknown"
        },
        {
          "Category": "Design",
          "PropertyName": "PressedFill",
          "RuleProviderType": "Unknown"
        },
        {
          "Category": "Design",
          "PropertyName": "HoverFill",
          "RuleProviderType": "Unknown"
        },
        {
          "Category": "Design",
          "PropertyName": "PressedBorderColor",
          "RuleProviderType": "Unknown"
        },
        {
          "Category": "Design",
          "PropertyName": "HoverBorderColor",
          "RuleProviderType": "Unknown"
        },
        {
          "Category": "Design",
          "PropertyName": "DisabledBorderColor",
          "RuleProviderType": "Unknown"
        },
        {
          "Category": "Design",
          "PropertyName": "BorderStyle",
          "RuleProviderType": "Unknown"
        },
        {
          "Category": "Design",
          "PropertyName": "FocusedBorderColor",
          "RuleProviderType": "Unknown"
        },
        {
          "Category": "Design",
          "PropertyName": "Fill",
          "RuleProviderType": "Unknown"
        },
        {
          "Category": "Design",
          "PropertyName": "Font",
          "RuleProviderType": "Unknown"
        },
        {
          "Category": "Design",
          "PropertyName": "FontWeight",
          "RuleProviderType": "Unknown"
        },
        {
          "Category": "Design",
          "PropertyName": "Color",
          "RuleProviderType": "Unknown"
        },
        {
          "Category": "Design",
          "PropertyName": "DisabledColor",
          "RuleProviderType": "Unknown"
        },
        {
          "Category": "Design",
          "PropertyName": "Width",
          "RuleProviderType": "Unknown"
        },
        {
          "Category": "Design",
          "PropertyName": "Height",
          "RuleProviderType": "Unknown"
        },
        {
          "Category": "Design",
          "PropertyName": "X",
          "RuleProviderType": "Unknown"
        },
        {
          "Category": "Design",
          "PropertyName": "Y",
          "RuleProviderType": "Unknown"
        },
        {
          "Category": "Design",
          "PropertyName": "DisplayMode",
          "RuleProviderType": "Unknown"
        },
        {
          "Category": "Design",
          "PropertyName": "ZIndex",
          "RuleProviderType": "Unknown"
        },
        {
          "Category": "Design",
          "PropertyName": "BorderThickness",
          "RuleProviderType": "Unknown"
        },
        {
          "Category": "Design",
          "PropertyName": "FocusedBorderThickness",
          "RuleProviderType": "Unknown"
        },
        {
          "Category": "Design",
          "PropertyName": "Size",
          "RuleProviderType": "Unknown"
        },
        {
          "Category": "Design",
          "PropertyName": "Italic",
          "RuleProviderType": "Unknown"
        },
        {
          "Category": "Design",
          "PropertyName": "PaddingTop",
          "RuleProviderType": "Unknown"
        },
        {
          "Category": "Design",
          "PropertyName": "PaddingRight",
          "RuleProviderType": "Unknown"
        },
        {
          "Category": "Design",
          "PropertyName": "PaddingBottom",
          "RuleProviderType": "Unknown"
        },
        {
          "Category": "Design",
          "PropertyName": "PaddingLeft",
          "RuleProviderType": "Unknown"
        },
        {
          "Category": "Behavior",
          "PropertyName": "OnSelect",
          "RuleProviderType": "User"
        }
      ],
      "StyleName": "defaultDatePickerStyle",
      "Type": "ControlInfo"
    },
    "DatePickerContainer": {
      "AllowAccessToGlobals": true,
      "ControlPropertyState": [
        "BorderColor",
        "BorderStyle",
        {
          "AFDDataSourceName": "",
          "AutoRuleBindingEnabled": false,
          "AutoRuleBindingString": "",
          "InvariantPropertyName": "Fill",
          "IsLockable": false,
          "NameMapSourceSchema": "?"
        },
        "X",
        "Y",
        "Width",
        "Height",
        "DisplayMode",
        "LayoutMode",
        "LayoutDirection",
        "LayoutAlignItems",
        "LayoutJustifyContent",
        "LayoutGap",
        "LayoutOverflowX",
        "LayoutOverflowY",
        "LayoutWrap",
        "DropShadow",
        "ZIndex",
        "RadiusTopLeft",
        "RadiusTopRight",
        "RadiusBottomLeft",
        "RadiusBottomRight"
      ],
      "HasDynamicProperties": false,
      "IsAutoGenerated": false,
      "IsComponentDefinition": false,
      "IsDataControl": false,
      "IsFromScreenLayout": false,
      "IsGroupControl": false,
      "IsLocked": false,
      "LayoutName": "",
      "MetaDataIDKey": "",
      "Name": "DatePickerContainer",
      "OptimizeForDevices": "Off",
      "ParentIndex": 0,
      "PersistMetaDataIDKey": false,
      "Properties": [
        {
          "Category": "Design",
          "PropertyName": "RadiusBottomRight",
          "RuleProviderType": "Unknown"
        },
        {
          "Category": "Design",
          "PropertyName": "RadiusBottomLeft",
          "RuleProviderType": "Unknown"
        },
        {
          "Category": "Design",
          "PropertyName": "RadiusTopRight",
          "RuleProviderType": "Unknown"
        },
        {
          "Category": "Design",
          "PropertyName": "RadiusTopLeft",
          "RuleProviderType": "Unknown"
        },
        {
          "Category": "Design",
          "PropertyName": "ZIndex",
          "RuleProviderType": "Unknown"
        },
        {
          "Category": "Design",
          "PropertyName": "DropShadow",
          "RuleProviderType": "Unknown"
        },
        {
          "Category": "Design",
          "PropertyName": "LayoutWrap",
          "RuleProviderType": "Unknown"
        },
        {
          "Category": "Design",
          "PropertyName": "LayoutOverflowY",
          "RuleProviderType": "Unknown"
        },
        {
          "Category": "Design",
          "PropertyName": "LayoutOverflowX",
          "RuleProviderType": "Unknown"
        },
        {
          "Category": "Design",
          "PropertyName": "LayoutGap",
          "RuleProviderType": "Unknown"
        },
        {
          "Category": "Design",
          "PropertyName": "LayoutJustifyContent",
          "RuleProviderType": "Unknown"
        },
        {
          "Category": "Design",
          "PropertyName": "LayoutAlignItems",
          "RuleProviderType": "Unknown"
        },
        {
          "Category": "Design",
          "PropertyName": "LayoutDirection",
          "RuleProviderType": "Unknown"
        },
        {
          "Category": "Design",
          "PropertyName": "LayoutMode",
          "RuleProviderType": "Unknown"
        },
        {
          "Category": "Design",
          "PropertyName": "DisplayMode",
          "RuleProviderType": "Unknown"
        },
        {
          "Category": "Design",
          "PropertyName": "Height",
          "RuleProviderType": "Unknown"
        },
        {
          "Category": "Design",
          "PropertyName": "Width",
          "RuleProviderType": "Unknown"
        },
        {
          "Category": "Design",
          "PropertyName": "Y",
          "RuleProviderType": "Unknown"
        },
        {
          "Category": "Design",
          "PropertyName": "X",
          "RuleProviderType": "Unknown"
        },
        {
          "Category": "Design",
          "PropertyName": "Fill",
          "RuleProviderType": "Unknown"
        },
        {
          "Category": "Design",
          "PropertyName": "BorderStyle",
          "RuleProviderType": "Unknown"
        },
        {
          "Category": "Design",
          "PropertyName": "BorderColor",
          "RuleProviderType": "Unknown"
        }
      ],
      "StyleName": "defaultGroupContainerStyle",
      "Type": "ControlInfo"
    },
    "Gallery2": {
      "AllowAccessToGlobals": true,
      "ControlPropertyState": [
        {
          "AFDDataSourceName": "",
          "AutoRuleBindingEnabled": false,
          "AutoRuleBindingString": "",
          "InvariantPropertyName": "Items",
          "IsLockable": false,
          "NameMapSourceSchema": "?"
        },
        "WrapCount",
        "TemplateSize",
        "TemplatePadding",
        "Layout",
        "Transition",
        "DelayItemLoading",
        "LoadingSpinner",
        "LoadingSpinnerColor",
        "DisplayMode",
        "BorderColor",
        "DisabledBorderColor",
        "PressedBorderColor",
        "HoverBorderColor",
        "BorderStyle",
        "FocusedBorderColor",
        "Fill",
        "DisabledFill",
        "PressedFill",
        "HoverFill",
        "X",
        "Y",
        "Width",
        "Height",
        "ZIndex"
      ],
      "GalleryTemplateChildName": "galleryTemplate2",
      "HasDynamicProperties": false,
      "IsAutoGenerated": false,
      "IsComponentDefinition": false,
      "IsDataControl": false,
      "IsFromScreenLayout": false,
      "IsGroupControl": false,
      "IsLocked": false,
      "LayoutName": "",
      "MetaDataIDKey": "",
      "Name": "Gallery2",
      "OptimizeForDevices": "Off",
      "ParentIndex": 0,
      "PersistMetaDataIDKey": false,
      "Properties": [
        {
          "Category": "Data",
          "PropertyName": "Items",
          "RuleProviderType": "Unknown"
        },
        {
          "Category": "Data",
          "PropertyName": "WrapCount",
          "RuleProviderType": "Unknown"
        },
        {
          "Category": "Design",
          "PropertyName": "TemplateSize",
          "RuleProviderType": "Unknown"
        },
        {
          "Category": "Design",
          "PropertyName": "TemplatePadding",
          "RuleProviderType": "Unknown"
        },
        {
          "Category": "Design",
          "PropertyName": "Layout",
          "RuleProviderType": "Unknown"
        },
        {
          "Category": "Design",
          "PropertyName": "Transition",
          "RuleProviderType": "Unknown"
        },
        {
          "Category": "Design",
          "PropertyName": "DelayItemLoading",
          "RuleProviderType": "Unknown"
        },
        {
          "Category": "Design",
          "PropertyName": "LoadingSpinner",
          "RuleProviderType": "Unknown"
        },
        {
          "Category": "Design",
          "PropertyName": "HoverFill",
          "RuleProviderType": "Unknown"
        },
        {
          "Category": "Design",
          "PropertyName": "DisplayMode",
          "RuleProviderType": "Unknown"
        },
        {
          "Category": "Design",
          "PropertyName": "BorderColor",
          "RuleProviderType": "Unknown"
        },
        {
          "Category": "Design",
          "PropertyName": "PressedFill",
          "RuleProviderType": "Unknown"
        },
        {
          "Category": "Design",
          "PropertyName": "DisabledFill",
          "RuleProviderType": "Unknown"
        },
        {
          "Category": "Design",
          "PropertyName": "FocusedBorderColor",
          "RuleProviderType": "Unknown"
        },
        {
          "Category": "Design",
          "PropertyName": "BorderStyle",
          "RuleProviderType": "Unknown"
        },
        {
          "Category": "Design",
          "PropertyName": "HoverBorderColor",
          "RuleProviderType": "Unknown"
        },
        {
          "Category": "Design",
          "PropertyName": "Fill",
          "RuleProviderType": "Unknown"
        },
        {
          "Category": "Design",
          "PropertyName": "PressedBorderColor",
          "RuleProviderType": "Unknown"
        },
        {
          "Category": "Design",
          "PropertyName": "DisabledBorderColor",
          "RuleProviderType": "Unknown"
        },
        {
          "Category": "Design",
          "PropertyName": "LoadingSpinnerColor",
          "RuleProviderType": "Unknown"
        },
        {
          "Category": "Design",
          "PropertyName": "X",
          "RuleProviderType": "Unknown"
        },
        {
          "Category": "Design",
          "PropertyName": "Y",
          "RuleProviderType": "Unknown"
        },
        {
          "Category": "Design",
          "PropertyName": "Width",
          "RuleProviderType": "Unknown"
        },
        {
          "Category": "Design",
          "PropertyName": "Height",
          "RuleProviderType": "Unknown"
        },
        {
          "Category": "Design",
          "PropertyName": "ZIndex",
          "RuleProviderType": "Unknown"
        }
      ],
      "StyleName": "defaultGalleryStyle",
      "Type": "ControlInfo"
    },
    "GalleryContainer": {
      "AllowAccessToGlobals": true,
      "ControlPropertyState": [
        "BorderColor",
        "BorderStyle",
        {
          "AFDDataSourceName": "",
          "AutoRuleBindingEnabled": false,
          "AutoRuleBindingString": "",
          "InvariantPropertyName": "Fill",
          "IsLockable": false,
          "NameMapSourceSchema": "?"
        },
        "X",
        "Y",
        "Width",
        "Height",
        "DisplayMode",
        "LayoutMode",
        "LayoutDirection",
        "LayoutAlignItems",
        "LayoutJustifyContent",
        "LayoutGap",
        "LayoutOverflowX",
        "LayoutOverflowY",
        "LayoutWrap",
        "DropShadow",
        "ZIndex",
        "RadiusTopLeft",
        "RadiusTopRight",
        "RadiusBottomLeft",
        "RadiusBottomRight"
      ],
      "HasDynamicProperties": false,
      "IsAutoGenerated": false,
      "IsComponentDefinition": false,
      "IsDataControl": false,
      "IsFromScreenLayout": false,
      "IsGroupControl": false,
      "IsLocked": false,
      "LayoutName": "",
      "MetaDataIDKey": "",
      "Name": "GalleryContainer",
      "OptimizeForDevices": "Off",
      "ParentIndex": 1,
      "PersistMetaDataIDKey": false,
      "Properties": [
        {
          "Category": "Design",
          "PropertyName": "BorderColor",
          "RuleProviderType": "Unknown"
        },
        {
          "Category": "Design",
          "PropertyName": "BorderStyle",
          "RuleProviderType": "Unknown"
        },
        {
          "Category": "Design",
          "PropertyName": "Fill",
          "RuleProviderType": "Unknown"
        },
        {
          "Category": "Design",
          "PropertyName": "X",
          "RuleProviderType": "Unknown"
        },
        {
          "Category": "Design",
          "PropertyName": "Y",
          "RuleProviderType": "Unknown"
        },
        {
          "Category": "Design",
          "PropertyName": "Width",
          "RuleProviderType": "Unknown"
        },
        {
          "Category": "Design",
          "PropertyName": "Height",
          "RuleProviderType": "Unknown"
        },
        {
          "Category": "Design",
          "PropertyName": "DisplayMode",
          "RuleProviderType": "Unknown"
        },
        {
          "Category": "Design",
          "PropertyName": "LayoutMode",
          "RuleProviderType": "Unknown"
        },
        {
          "Category": "Design",
          "PropertyName": "LayoutDirection",
          "RuleProviderType": "Unknown"
        },
        {
          "Category": "Design",
          "PropertyName": "LayoutAlignItems",
          "RuleProviderType": "Unknown"
        },
        {
          "Category": "Design",
          "PropertyName": "LayoutJustifyContent",
          "RuleProviderType": "Unknown"
        },
        {
          "Category": "Design",
          "PropertyName": "LayoutGap",
          "RuleProviderType": "Unknown"
        },
        {
          "Category": "Design",
          "PropertyName": "LayoutOverflowX",
          "RuleProviderType": "Unknown"
        },
        {
          "Category": "Design",
          "PropertyName": "LayoutOverflowY",
          "RuleProviderType": "Unknown"
        },
        {
          "Category": "Design",
          "PropertyName": "LayoutWrap",
          "RuleProviderType": "Unknown"
        },
        {
          "Category": "Design",
          "PropertyName": "DropShadow",
          "RuleProviderType": "Unknown"
        },
        {
          "Category": "Design",
          "PropertyName": "ZIndex",
          "RuleProviderType": "Unknown"
        },
        {
          "Category": "Design",
          "PropertyName": "RadiusTopLeft",
          "RuleProviderType": "Unknown"
        },
        {
          "Category": "Design",
          "PropertyName": "RadiusTopRight",
          "RuleProviderType": "Unknown"
        },
        {
          "Category": "Design",
          "PropertyName": "RadiusBottomLeft",
          "RuleProviderType": "Unknown"
        },
        {
          "Category": "Design",
          "PropertyName": "RadiusBottomRight",
          "RuleProviderType": "Unknown"
        }
      ],
      "StyleName": "defaultGroupContainerStyle",
      "Type": "ControlInfo"
    },
    "galleryTemplate2": {
      "AllowAccessToGlobals": true,
      "ControlPropertyState": [
        "TemplateFill"
      ],
      "HasDynamicProperties": false,
      "IsAutoGenerated": false,
      "IsComponentDefinition": false,
      "IsDataControl": true,
      "IsFromScreenLayout": false,
      "IsGroupControl": false,
      "IsLocked": false,
      "LayoutName": "",
      "MetaDataIDKey": "",
      "Name": "galleryTemplate2",
      "OptimizeForDevices": "Off",
      "ParentIndex": 0,
      "PersistMetaDataIDKey": false,
      "Properties": [
        {
          "Category": "Design",
          "PropertyName": "TemplateFill",
          "RuleProviderType": "Unknown"
        }
      ],
      "StyleName": "",
      "Type": "ControlInfo"
    },
    "Joining Date": {
      "AllowAccessToGlobals": true,
      "ControlPropertyState": [
        "Live",
        "Overflow",
        {
          "AFDDataSourceName": "",
          "AutoRuleBindingEnabled": false,
          "AutoRuleBindingString": "ThisItem.Name",
          "InvariantPropertyName": "Text",
          "IsLockable": false,
          "NameMapSourceSchema": "?"
        },
        "Role",
        "Color",
        "DisabledColor",
        "PressedColor",
        "HoverColor",
        "BorderColor",
        "DisabledBorderColor",
        "PressedBorderColor",
        "HoverBorderColor",
        "BorderStyle",
        "FocusedBorderColor",
        "Fill",
        "DisabledFill",
        "PressedFill",
        "HoverFill",
        "Font",
        "FontWeight",
        "Align",
        "VerticalAlign",
        "X",
        "Y",
        "Width",
        "Height",
        "DisplayMode",
        "OnSelect",
        "ZIndex",
        "PaddingTop",
        "PaddingRight",
        "PaddingBottom",
        "PaddingLeft",
        "TabIndex",
        "Size"
      ],
      "HasDynamicProperties": false,
      "IsAutoGenerated": false,
      "IsComponentDefinition": false,
      "IsDataControl": false,
      "IsFromScreenLayout": false,
      "IsGroupControl": false,
      "IsLocked": false,
      "LayoutName": "",
      "MetaDataIDKey": "%TemplateBrowseGallerySubtitle.ID%",
      "Name": "Joining Date",
      "OptimizeForDevices": "Off",
      "ParentIndex": 2,
      "PersistMetaDataIDKey": false,
      "Properties": [
        {
          "Category": "Data",
          "PropertyName": "Role",
          "RuleProviderType": "Unknown"
        },
        {
          "Category": "Data",
          "PropertyName": "Text",
          "RuleProviderType": "Unknown"
        },
        {
          "Category": "Data",
          "PropertyName": "Live",
          "RuleProviderType": "Unknown"
        },
        {
          "Category": "Design",
          "PropertyName": "Font",
          "RuleProviderType": "Unknown"
        },
        {
          "Category": "Design",
          "PropertyName": "DisabledFill",
          "RuleProviderType": "Unknown"
        },
        {
          "Category": "Design",
          "PropertyName": "Fill",
          "RuleProviderType": "Unknown"
        },
        {
          "Category": "Design",
          "PropertyName": "BorderStyle",
          "RuleProviderType": "Unknown"
        },
        {
          "Category": "Design",
          "PropertyName": "DisabledBorderColor",
          "RuleProviderType": "Unknown"
        },
        {
          "Category": "Design",
          "PropertyName": "BorderColor",
          "RuleProviderType": "Unknown"
        },
        {
          "Category": "Design",
          "PropertyName": "Y",
          "RuleProviderType": "Unknown"
        },
        {
          "Category": "Design",
          "PropertyName": "Align",
          "RuleProviderType": "Unknown"
        },
        {
          "Category": "Design",
          "PropertyName": "DisabledColor",
          "RuleProviderType": "Unknown"
        },
        {
          "Category": "Design",
          "PropertyName": "Color",
          "RuleProviderType": "Unknown"
        },
        {
          "Category": "Design",
          "PropertyName": "TabIndex",
          "RuleProviderType": "Unknown"
        },
        {
          "Category": "Design",
          "PropertyName": "PaddingLeft",
          "RuleProviderType": "Unknown"
        },
        {
          "Category": "Design",
          "PropertyName": "PaddingBottom",
          "RuleProviderType": "Unknown"
        },
        {
          "Category": "Design",
          "PropertyName": "Overflow",
          "RuleProviderType": "Unknown"
        },
        {
          "Category": "Design",
          "PropertyName": "PaddingRight",
          "RuleProviderType": "Unknown"
        },
        {
          "Category": "Design",
          "PropertyName": "PaddingTop",
          "RuleProviderType": "Unknown"
        },
        {
          "Category": "Design",
          "PropertyName": "Height",
          "RuleProviderType": "Unknown"
        },
        {
          "Category": "Design",
          "PropertyName": "HoverFill",
          "RuleProviderType": "Unknown"
        },
        {
          "Category": "Design",
          "PropertyName": "DisplayMode",
          "RuleProviderType": "Unknown"
        },
        {
          "Category": "Design",
          "PropertyName": "VerticalAlign",
          "RuleProviderType": "Unknown"
        },
        {
          "Category": "Design",
          "PropertyName": "Size",
          "RuleProviderType": "Unknown"
        },
        {
          "Category": "Design",
          "PropertyName": "ZIndex",
          "RuleProviderType": "Unknown"
        },
        {
          "Category": "Design",
          "PropertyName": "PressedFill",
          "RuleProviderType": "Unknown"
        },
        {
          "Category": "Design",
          "PropertyName": "FontWeight",
          "RuleProviderType": "Unknown"
        },
        {
          "Category": "Design",
          "PropertyName": "FocusedBorderColor",
          "RuleProviderType": "Unknown"
        },
        {
          "Category": "Design",
          "PropertyName": "HoverBorderColor",
          "RuleProviderType": "Unknown"
        },
        {
          "Category": "Design",
          "PropertyName": "PressedBorderColor",
          "RuleProviderType": "Unknown"
        },
        {
          "Category": "Design",
          "PropertyName": "HoverColor",
          "RuleProviderType": "Unknown"
        },
        {
          "Category": "Design",
          "PropertyName": "PressedColor",
          "RuleProviderType": "Unknown"
        },
        {
          "Category": "Design",
          "PropertyName": "Width",
          "RuleProviderType": "Unknown"
        },
        {
          "Category": "Design",
          "PropertyName": "X",
          "RuleProviderType": "Unknown"
        },
        {
          "Category": "Behavior",
          "PropertyName": "OnSelect",
          "RuleProviderType": "Unknown"
        }
      ],
      "StyleName": "subtitleLabelStyle_galleryLayouts_ver5",
      "Type": "ControlInfo"
    },
    "Name": {
      "AllowAccessToGlobals": true,
      "ControlPropertyState": [
        "Live",
        "Overflow",
        "Text",
        "Role",
        "Color",
        "DisabledColor",
        "PressedColor",
        "HoverColor",
        "BorderColor",
        "DisabledBorderColor",
        "PressedBorderColor",
        "HoverBorderColor",
        "BorderStyle",
        "FocusedBorderColor",
        "Fill",
        "DisabledFill",
        "PressedFill",
        "HoverFill",
        "Font",
        "FontWeight",
        "Align",
        "VerticalAlign",
        "X",
        "Y",
        "Width",
        "Height",
        "DisplayMode",
        "OnSelect",
        "ZIndex",
        "PaddingTop",
        "PaddingRight",
        "PaddingBottom",
        "PaddingLeft",
        "TabIndex",
        "Size"
      ],
      "HasDynamicProperties": false,
      "IsAutoGenerated": false,
      "IsComponentDefinition": false,
      "IsDataControl": false,
      "IsFromScreenLayout": false,
      "IsGroupControl": false,
      "IsLocked": false,
      "LayoutName": "",
      "MetaDataIDKey": "%TemplateBrowseGalleryTitle.ID%",
      "Name": "Name",
      "OptimizeForDevices": "Off",
      "ParentIndex": 1,
      "PersistMetaDataIDKey": false,
      "Properties": [
        {
          "Category": "Data",
          "PropertyName": "Role",
          "RuleProviderType": "Unknown"
        },
        {
          "Category": "Data",
          "PropertyName": "Text",
          "RuleProviderType": "Unknown"
        },
        {
          "Category": "Data",
          "PropertyName": "Live",
          "RuleProviderType": "Unknown"
        },
        {
          "Category": "Design",
          "PropertyName": "FontWeight",
          "RuleProviderType": "Unknown"
        },
        {
          "Category": "Design",
          "PropertyName": "Font",
          "RuleProviderType": "Unknown"
        },
        {
          "Category": "Design",
          "PropertyName": "DisabledFill",
          "RuleProviderType": "Unknown"
        },
        {
          "Category": "Design",
          "PropertyName": "Fill",
          "RuleProviderType": "Unknown"
        },
        {
          "Category": "Design",
          "PropertyName": "BorderStyle",
          "RuleProviderType": "Unknown"
        },
        {
          "Category": "Design",
          "PropertyName": "DisabledBorderColor",
          "RuleProviderType": "Unknown"
        },
        {
          "Category": "Design",
          "PropertyName": "PaddingBottom",
          "RuleProviderType": "Unknown"
        },
        {
          "Category": "Design",
          "PropertyName": "PaddingRight",
          "RuleProviderType": "Unknown"
        },
        {
          "Category": "Design",
          "PropertyName": "BorderColor",
          "RuleProviderType": "Unknown"
        },
        {
          "Category": "Design",
          "PropertyName": "DisabledColor",
          "RuleProviderType": "Unknown"
        },
        {
          "Category": "Design",
          "PropertyName": "PaddingTop",
          "RuleProviderType": "Unknown"
        },
        {
          "Category": "Design",
          "PropertyName": "ZIndex",
          "RuleProviderType": "Unknown"
        },
        {
          "Category": "Design",
          "PropertyName": "Color",
          "RuleProviderType": "Unknown"
        },
        {
          "Category": "Design",
          "PropertyName": "DisplayMode",
          "RuleProviderType": "Unknown"
        },
        {
          "Category": "Design",
          "PropertyName": "X",
          "RuleProviderType": "Unknown"
        },
        {
          "Category": "Design",
          "PropertyName": "VerticalAlign",
          "RuleProviderType": "Unknown"
        },
        {
          "Category": "Design",
          "PropertyName": "Overflow",
          "RuleProviderType": "Unknown"
        },
        {
          "Category": "Design",
          "PropertyName": "PressedBorderColor",
          "RuleProviderType": "Unknown"
        },
        {
          "Category": "Design",
          "PropertyName": "HoverColor",
          "RuleProviderType": "Unknown"
        },
        {
          "Category": "Design",
          "PropertyName": "PressedColor",
          "RuleProviderType": "Unknown"
        },
        {
          "Category": "Design",
          "PropertyName": "PaddingLeft",
          "RuleProviderType": "Unknown"
        },
        {
          "Category": "Design",
          "PropertyName": "TabIndex",
          "RuleProviderType": "Unknown"
        },
        {
          "Category": "Design",
          "PropertyName": "Align",
          "RuleProviderType": "Unknown"
        },
        {
          "Category": "Design",
          "PropertyName": "Size",
          "RuleProviderType": "Unknown"
        },
        {
          "Category": "Design",
          "PropertyName": "Width",
          "RuleProviderType": "Unknown"
        },
        {
          "Category": "Design",
          "PropertyName": "Y",
          "RuleProviderType": "Unknown"
        },
        {
          "Category": "Design",
          "PropertyName": "Height",
          "RuleProviderType": "Unknown"
        },
        {
          "Category": "Design",
          "PropertyName": "HoverFill",
          "RuleProviderType": "Unknown"
        },
        {
          "Category": "Design",
          "PropertyName": "HoverBorderColor",
          "RuleProviderType": "Unknown"
        },
        {
          "Category": "Design",
          "PropertyName": "FocusedBorderColor",
          "RuleProviderType": "Unknown"
        },
        {
          "Category": "Design",
          "PropertyName": "PressedFill",
          "RuleProviderType": "Unknown"
        },
        {
          "Category": "Behavior",
          "PropertyName": "OnSelect",
          "RuleProviderType": "Unknown"
        }
      ],
      "StyleName": "titleLabelStyle_galleryLayouts_ver5",
      "Type": "ControlInfo"
    },
    "Progress2": {
      "AllowAccessToGlobals": true,
      "ControlPropertyState": [
        "X",
        "Y",
        "Width",
        {
          "AFDDataSourceName": "",
          "AutoRuleBindingEnabled": false,
          "AutoRuleBindingString": "",
          "InvariantPropertyName": "Height",
          "IsLockable": false,
          "NameMapSourceSchema": "?"
        },
        "DisplayMode",
        "ZIndex",
        {
          "AFDDataSourceName": "",
          "AutoRuleBindingEnabled": false,
          "AutoRuleBindingString": "",
          "InvariantPropertyName": "Indeterminate",
          "IsLockable": false,
          "NameMapSourceSchema": "?"
        }
      ],
      "HasDynamicProperties": false,
      "IsAutoGenerated": false,
      "IsComponentDefinition": false,
      "IsDataControl": false,
      "IsFromScreenLayout": false,
      "IsGroupControl": false,
      "IsLocked": false,
      "LayoutName": "",
      "MetaDataIDKey": "",
      "Name": "Progress2",
      "OptimizeForDevices": "Off",
      "ParentIndex": 4,
      "PersistMetaDataIDKey": false,
      "Properties": [
        {
          "Category": "Data",
          "PropertyName": "Indeterminate",
          "RuleProviderType": "Unknown"
        },
        {
          "Category": "Design",
          "PropertyName": "X",
          "RuleProviderType": "Unknown"
        },
        {
          "Category": "Design",
          "PropertyName": "Y",
          "RuleProviderType": "Unknown"
        },
        {
          "Category": "Design",
          "PropertyName": "Width",
          "RuleProviderType": "Unknown"
        },
        {
          "Category": "Design",
          "PropertyName": "Height",
          "RuleProviderType": "Unknown"
        },
        {
          "Category": "Design",
          "PropertyName": "DisplayMode",
          "RuleProviderType": "Unknown"
        },
        {
          "Category": "Design",
          "PropertyName": "ZIndex",
          "RuleProviderType": "Unknown"
        }
      ],
      "StyleName": "",
      "Type": "ControlInfo"
    }
  },
  "TopParentName": "DateFilter_Assignment_Screen"
}